dieterpy/__init__.py
dieterpy/__main__.py
dieterpy/config/__init__.py
dieterpy/config/global_config.py
dieterpy/config/setting.py
dieterpy/scripts/__init__.py
dieterpy/scripts/gams_tools.py
dieterpy/scripts/gdx_handler.py
dieterpy/scripts/input_data.py
dieterpy/scripts/output_data.py
dieterpy/scripts/report.py
dieterpy/scripts/runopt.py
dieterpy/scripts/solve.py
dieterpy/scripts/util.py
dieterpy/templates/templates_info.json
dieterpy/templates/base/ResultsAnalysis.ipynb
dieterpy/templates/base/manage.py
dieterpy/templates/base/.vscode/launch.json
dieterpy/templates/base/project_files/data_input/static_input.xlsx
dieterpy/templates/base/project_files/data_input/timeseries_input.xlsx
dieterpy/templates/base/project_files/iterationfiles/iteration_data.xlsx
dieterpy/templates/base/project_files/iterationfiles/iteration_table.csv
dieterpy/templates/base/project_files/model/DIETER.gms
dieterpy/templates/base/project_files/model/WarningNOTE.txt
dieterpy/templates/base/project_files/model/dataload.gms
dieterpy/templates/base/project_files/model/dieterpy_1_globalopt.gms
dieterpy/templates/base/project_files/model/dieterpy_2_nodesandparsload.gms
dieterpy/templates/base/project_files/model/dieterpy_3_definenewconstr.gms
dieterpy/templates/base/project_files/model/dieterpy_4_developnewconstr.gms
dieterpy/templates/base/project_files/model/dieterpy_5_includenewconstr.gms
dieterpy/templates/base/project_files/model/dieterpy_6_solveropt.gms
dieterpy/templates/base/project_files/model/dieterpy_7_custom.gms
dieterpy/templates/base/project_files/model/fix.gms
dieterpy/templates/base/project_files/model/model.gms
dieterpy/templates/base/project_files/model/project.gpr
dieterpy/templates/base/project_files/model/report.gms
dieterpy/templates/base/project_files/model/scenario.gms
dieterpy/templates/base/project_files/settings/constraints_list.csv
dieterpy/templates/base/project_files/settings/features_node_selection.csv
dieterpy-1.6.2.dist-info/LICENSE
dieterpy-1.6.2.dist-info/METADATA
dieterpy-1.6.2.dist-info/WHEEL
dieterpy-1.6.2.dist-info/entry_points.txt
dieterpy-1.6.2.dist-info/top_level.txt
dieterpy-1.6.2.dist-info/RECORD
