Metadata-Version: 2.1
Name: dieterpy
Version: 1.6.2
Summary: DIETERpy GAMS-Python framework of a power system model DIETER
Author: Carlos Gaete-Morales
Author-email: cdgaete@gmail.com
Classifier: Intended Audience :: Science/Research
Classifier: License :: OSI Approved :: MIT License
Classifier: Operating System :: MacOS :: MacOS X
Classifier: Operating System :: Microsoft :: Windows
Classifier: Operating System :: POSIX
Classifier: Programming Language :: Python
Classifier: Programming Language :: Python :: 3
Classifier: Programming Language :: Python :: 3.6
Classifier: Programming Language :: Python :: 3.7
Classifier: Programming Language :: Python :: 3.8
Classifier: Programming Language :: Python :: 3.9
Classifier: Programming Language :: Python :: 3.10
Classifier: Topic :: Scientific/Engineering
License-File: LICENSE
Requires-Dist: numpy
Requires-Dist: pandas
Requires-Dist: pyyaml
Requires-Dist: mgzip
Requires-Dist: appdirs
Requires-Dist: wget
Requires-Dist: exceltogdx
Requires-Dist: loguru
